testPyHHB/__init__.py
testPyHHB/file1.py
testPyHHB/file2.py
pyHBB-0.1.0.dist-info/LICENSE
pyHBB-0.1.0.dist-info/METADATA
pyHBB-0.1.0.dist-info/WHEEL
pyHBB-0.1.0.dist-info/top_level.txt
pyHBB-0.1.0.dist-info/RECORD
